MANIFEST.in
README.rst
setup.py
docs/HISTORY.txt
docs/LICENSE.GPL
docs/LICENSE.txt
ftw/__init__.py
ftw.notification.base.egg-info/PKG-INFO
ftw.notification.base.egg-info/SOURCES.txt
ftw.notification.base.egg-info/dependency_links.txt
ftw.notification.base.egg-info/entry_points.txt
ftw.notification.base.egg-info/namespace_packages.txt
ftw.notification.base.egg-info/not-zip-safe
ftw.notification.base.egg-info/requires.txt
ftw.notification.base.egg-info/top_level.txt
ftw/notification/__init__.py
ftw/notification/base/__init__.py
ftw/notification/base/configure.zcml
ftw/notification/base/interfaces.py
ftw/notification/base/notifier.py
ftw/notification/base/testing.py
ftw/notification/base/vocabularies.py
ftw/notification/base/adapters/__init__.py
ftw/notification/base/adapters/configure.zcml
ftw/notification/base/adapters/notifier.py
ftw/notification/base/browser/__init__.py
ftw/notification/base/browser/configure.zcml
ftw/notification/base/browser/notification_form.pt
ftw/notification/base/browser/views.py
ftw/notification/base/events/__init__.py
ftw/notification/base/events/configure.zcml
ftw/notification/base/events/events.py
ftw/notification/base/events/handlers.py
ftw/notification/base/locales/ftw.notification.base-manual.pot
ftw/notification/base/locales/ftw.notification.base.pot
ftw/notification/base/locales/de/LC_MESSAGES/ftw.notification.base.po
ftw/notification/base/locales/en/LC_MESSAGES/ftw.notification.base.po
ftw/notification/base/locales/fr/LC_MESSAGES/ftw.notification.base.po
ftw/notification/base/profiles/default/metadata.xml
ftw/notification/base/profiles/default/propertiestool.xml
ftw/notification/base/tests/__init__.py
ftw/notification/base/tests/test_notification_form.py
ftw/notification/base/tests/test_redirect.py
ftw/notification/base/tests/test_resolve_groups.py
ftw/notification/base/upgrades/__init__.py
ftw/notification/base/upgrades/20151019173839_remove_skins_directory/__init__.py
ftw/notification/base/upgrades/20151019173839_remove_skins_directory/skins.xml
ftw/notification/base/upgrades/20151019173839_remove_skins_directory/upgrade.py
ftw/notification/base/viewlets/__init__.py
ftw/notification/base/viewlets/configure.zcml
ftw/notification/base/viewlets/notificationform.pt
ftw/notification/base/viewlets/notificationform.py