Metadata-Version: 1.1
Name: ftw.notification.base
Version: 1.3.0
Summary: Send notifications when editing a plone content.
Home-page: https://github.com/4teamwork/ftw.notification.base
Author: Jonas Baumann
Author-email: mailto:info@4teamwork.ch
License: GPL2
Keywords: ftw notification base plone
Platform: UNKNOWN
Classifier: Framework :: Plone
Classifier: Framework :: Plone :: 4.3
Classifier: License :: OSI Approved :: GNU General Public License (GPL)
Classifier: Programming Language :: Python
Classifier: Programming Language :: Python :: 2.7
Classifier: Topic :: Software Development :: Libraries :: Python Modules
